<annotation>
	<folder>train</folder>
	<filename>i3.jpg</filename>
	<path>/home/bussi/Documentos/tcc/Experiments/LettuceDataset/train/i3.jpg</path>
	<source>
		<database>Unknown</database>
	</source>
	<size>
		<width>3000</width>
		<height>4000</height>
		<depth>3</depth>
	</size>
	<segmented>0</segmented>
	<object>
		<name>weed</name>
		<pose>Unspecified</pose>
		<truncated>0</truncated>
		<difficult>0</difficult>
		<bndbox>
			<xmin>531</xmin>
			<ymin>3446</ymin>
			<xmax>625</xmax>
			<ymax>3565</ymax>
		</bndbox>
	</object>
	<object>
		<name>weed</name>
		<pose>Unspecified</pose>
		<truncated>0</truncated>
		<difficult>0</difficult>
		<bndbox>
			<xmin>1012</xmin>
			<ymin>3596</ymin>
			<xmax>1137</xmax>
			<ymax>3709</ymax>
		</bndbox>
	</object>
	<object>
		<name>weed</name>
		<pose>Unspecified</pose>
		<truncated>0</truncated>
		<difficult>0</difficult>
		<bndbox>
			<xmin>1450</xmin>
			<ymin>3690</ymin>
			<xmax>1581</xmax>
			<ymax>3809</ymax>
		</bndbox>
	</object>
	<object>
		<name>weed</name>
		<pose>Unspecified</pose>
		<truncated>0</truncated>
		<difficult>0</difficult>
		<bndbox>
			<xmin>1831</xmin>
			<ymin>3859</ymin>
			<xmax>1987</xmax>
			<ymax>3959</ymax>
		</bndbox>
	</object>
	<object>
		<name>weed</name>
		<pose>Unspecified</pose>
		<truncated>0</truncated>
		<difficult>0</difficult>
		<bndbox>
			<xmin>2618</xmin>
			<ymin>3827</ymin>
			<xmax>2706</xmax>
			<ymax>3948</ymax>
		</bndbox>
	</object>
	<object>
		<name>weed</name>
		<pose>Unspecified</pose>
		<truncated>0</truncated>
		<difficult>0</difficult>
		<bndbox>
			<xmin>2143</xmin>
			<ymin>3840</ymin>
			<xmax>2243</xmax>
			<ymax>3952</ymax>
		</bndbox>
	</object>
	<object>
		<name>weed</name>
		<pose>Unspecified</pose>
		<truncated>0</truncated>
		<difficult>0</difficult>
		<bndbox>
			<xmin>2362</xmin>
			<ymin>3884</ymin>
			<xmax>2437</xmax>
			<ymax>3965</ymax>
		</bndbox>
	</object>
	<object>
		<name>weed</name>
		<pose>Unspecified</pose>
		<truncated>0</truncated>
		<difficult>0</difficult>
		<bndbox>
			<xmin>212</xmin>
			<ymin>2920</ymin>
			<xmax>293</xmax>
			<ymax>3014</ymax>
		</bndbox>
	</object>
	<object>
		<name>weed</name>
		<pose>Unspecified</pose>
		<truncated>0</truncated>
		<difficult>0</difficult>
		<bndbox>
			<xmin>475</xmin>
			<ymin>2848</ymin>
			<xmax>571</xmax>
			<ymax>2961</ymax>
		</bndbox>
	</object>
	<object>
		<name>weed</name>
		<pose>Unspecified</pose>
		<truncated>0</truncated>
		<difficult>0</difficult>
		<bndbox>
			<xmin>746</xmin>
			<ymin>3025</ymin>
			<xmax>827</xmax>
			<ymax>3123</ymax>
		</bndbox>
	</object>
	<object>
		<name>weed</name>
		<pose>Unspecified</pose>
		<truncated>0</truncated>
		<difficult>0</difficult>
		<bndbox>
			<xmin>105</xmin>
			<ymin>3909</ymin>
			<xmax>171</xmax>
			<ymax>3998</ymax>
		</bndbox>
	</object>
	<object>
		<name>weed</name>
		<pose>Unspecified</pose>
		<truncated>0</truncated>
		<difficult>0</difficult>
		<bndbox>
			<xmin>2554</xmin>
			<ymin>3366</ymin>
			<xmax>2621</xmax>
			<ymax>3437</ymax>
		</bndbox>
	</object>
	<object>
		<name>weed</name>
		<pose>Unspecified</pose>
		<truncated>0</truncated>
		<difficult>0</difficult>
		<bndbox>
			<xmin>2348</xmin>
			<ymin>3179</ymin>
			<xmax>2439</xmax>
			<ymax>3254</ymax>
		</bndbox>
	</object>
	<object>
		<name>weed</name>
		<pose>Unspecified</pose>
		<truncated>0</truncated>
		<difficult>0</difficult>
		<bndbox>
			<xmin>2089</xmin>
			<ymin>3673</ymin>
			<xmax>2138</xmax>
			<ymax>3712</ymax>
		</bndbox>
	</object>
	<object>
		<name>weed</name>
		<pose>Unspecified</pose>
		<truncated>0</truncated>
		<difficult>0</difficult>
		<bndbox>
			<xmin>2325</xmin>
			<ymin>2784</ymin>
			<xmax>2456</xmax>
			<ymax>2915</ymax>
		</bndbox>
	</object>
	<object>
		<name>weed</name>
		<pose>Unspecified</pose>
		<truncated>0</truncated>
		<difficult>0</difficult>
		<bndbox>
			<xmin>1644</xmin>
			<ymin>2834</ymin>
			<xmax>1750</xmax>
			<ymax>2953</ymax>
		</bndbox>
	</object>
	<object>
		<name>weed</name>
		<pose>Unspecified</pose>
		<truncated>0</truncated>
		<difficult>0</difficult>
		<bndbox>
			<xmin>1468</xmin>
			<ymin>2609</ymin>
			<xmax>1518</xmax>
			<ymax>2671</ymax>
		</bndbox>
	</object>
	<object>
		<name>weed</name>
		<pose>Unspecified</pose>
		<truncated>0</truncated>
		<difficult>0</difficult>
		<bndbox>
			<xmin>1175</xmin>
			<ymin>2534</ymin>
			<xmax>1256</xmax>
			<ymax>2665</ymax>
		</bndbox>
	</object>
	<object>
		<name>weed</name>
		<pose>Unspecified</pose>
		<truncated>0</truncated>
		<difficult>0</difficult>
		<bndbox>
			<xmin>593</xmin>
			<ymin>2309</ymin>
			<xmax>756</xmax>
			<ymax>2452</ymax>
		</bndbox>
	</object>
	<object>
		<name>weed</name>
		<pose>Unspecified</pose>
		<truncated>0</truncated>
		<difficult>0</difficult>
		<bndbox>
			<xmin>306</xmin>
			<ymin>2102</ymin>
			<xmax>381</xmax>
			<ymax>2240</ymax>
		</bndbox>
	</object>
	<object>
		<name>weed</name>
		<pose>Unspecified</pose>
		<truncated>0</truncated>
		<difficult>0</difficult>
		<bndbox>
			<xmin>56</xmin>
			<ymin>1865</ymin>
			<xmax>262</xmax>
			<ymax>1977</ymax>
		</bndbox>
	</object>
	<object>
		<name>weed</name>
		<pose>Unspecified</pose>
		<truncated>0</truncated>
		<difficult>0</difficult>
		<bndbox>
			<xmin>68</xmin>
			<ymin>1709</ymin>
			<xmax>175</xmax>
			<ymax>1790</ymax>
		</bndbox>
	</object>
	<object>
		<name>weed</name>
		<pose>Unspecified</pose>
		<truncated>0</truncated>
		<difficult>0</difficult>
		<bndbox>
			<xmin>1783</xmin>
			<ymin>2339</ymin>
			<xmax>2006</xmax>
			<ymax>2611</ymax>
		</bndbox>
	</object>
	<object>
		<name>weed</name>
		<pose>Unspecified</pose>
		<truncated>0</truncated>
		<difficult>0</difficult>
		<bndbox>
			<xmin>2342</xmin>
			<ymin>2472</ymin>
			<xmax>2422</xmax>
			<ymax>2625</ymax>
		</bndbox>
	</object>
	<object>
		<name>weed</name>
		<pose>Unspecified</pose>
		<truncated>0</truncated>
		<difficult>0</difficult>
		<bndbox>
			<xmin>2261</xmin>
			<ymin>1611</ymin>
			<xmax>2369</xmax>
			<ymax>1736</ymax>
		</bndbox>
	</object>
	<object>
		<name>weed</name>
		<pose>Unspecified</pose>
		<truncated>0</truncated>
		<difficult>0</difficult>
		<bndbox>
			<xmin>2100</xmin>
			<ymin>1464</ymin>
			<xmax>2183</xmax>
			<ymax>1531</ymax>
		</bndbox>
	</object>
	<object>
		<name>weed</name>
		<pose>Unspecified</pose>
		<truncated>0</truncated>
		<difficult>0</difficult>
		<bndbox>
			<xmin>931</xmin>
			<ymin>2000</ymin>
			<xmax>1033</xmax>
			<ymax>2053</ymax>
		</bndbox>
	</object>
	<object>
		<name>weed</name>
		<pose>Unspecified</pose>
		<truncated>0</truncated>
		<difficult>0</difficult>
		<bndbox>
			<xmin>892</xmin>
			<ymin>1744</ymin>
			<xmax>1022</xmax>
			<ymax>1850</ymax>
		</bndbox>
	</object>
	<object>
		<name>weed</name>
		<pose>Unspecified</pose>
		<truncated>0</truncated>
		<difficult>0</difficult>
		<bndbox>
			<xmin>19</xmin>
			<ymin>1000</ymin>
			<xmax>175</xmax>
			<ymax>1078</ymax>
		</bndbox>
	</object>
	<object>
		<name>weed</name>
		<pose>Unspecified</pose>
		<truncated>0</truncated>
		<difficult>0</difficult>
		<bndbox>
			<xmin>1243</xmin>
			<ymin>665</ymin>
			<xmax>1368</xmax>
			<ymax>784</ymax>
		</bndbox>
	</object>
	<object>
		<name>crop</name>
		<pose>Unspecified</pose>
		<truncated>0</truncated>
		<difficult>0</difficult>
		<bndbox>
			<xmin>1406</xmin>
			<ymin>1503</ymin>
			<xmax>1750</xmax>
			<ymax>1986</ymax>
		</bndbox>
	</object>
</annotation>
